flask_env_settings.py
setup.py
flask_env_settings.egg-info/PKG-INFO
flask_env_settings.egg-info/SOURCES.txt
flask_env_settings.egg-info/dependency_links.txt
flask_env_settings.egg-info/requires.txt
flask_env_settings.egg-info/top_level.txt